kaas_cli/__init__.py
kaas_cli/__main__.py
kaas_cli/cli.py
kaas_cli/client.py
kaas_cli/config.py
kaas_cli/constants.py
kaas_cli/hello.py
kaas_cli/py.typed
kaas_cli/run_forge.py
kaas_cli/run_kontrol.py
kaas_cli/types.py
kaas_cli/utils.py
kaas_cli-0.1.292.dist-info/LICENSE
kaas_cli-0.1.292.dist-info/METADATA
kaas_cli-0.1.292.dist-info/WHEEL
kaas_cli-0.1.292.dist-info/entry_points.txt
kaas_cli-0.1.292.dist-info/RECORD
