Metadata-Version: 2.1
Name: kaas-cli
Version: 0.1.292
Summary: Command line utility for K as a Service
Author: Runtime Verification, Inc.
Author-email: contact@runtimeverification.com
Requires-Python: >=3.11,<4.0
Classifier: Programming Language :: Python :: 3
Classifier: Programming Language :: Python :: 3.11
Classifier: Programming Language :: Python :: 3.12
Classifier: Programming Language :: Python :: 3.13
Requires-Dist: click (>=8.0.1,<9.0.0)
Requires-Dist: dacite (>=1.8.1,<2.0.0)
Requires-Dist: docker (>=7.1.0,<8.0.0)
Requires-Dist: gql[requests] (>=3.4.0,<4.0.0)
Requires-Dist: hurry-filesize (>=0.9,<0.10)
Requires-Dist: jmespath (>=1.0.1,<2.0.0)
Requires-Dist: pandas (>=2.2.2,<3.0.0)
Requires-Dist: pandas-stubs (>=2.2.2.240603,<3.0.0.0)
Requires-Dist: pytest (>=8.0.1,<9.0.0)
Requires-Dist: pytest-watch (>=4.2.0,<5.0.0)
Requires-Dist: python-dotenv (>=1.0.1,<2.0.0)
Requires-Dist: requests (>=2.31.0,<3.0.0)
Requires-Dist: tomlkit (>=0.13.2,<0.14.0)
Requires-Dist: types-jmespath (>=1.0.2.20240106,<2.0.0.0)
Requires-Dist: urllib3 (>=1.25.4,<2.1)
